[
    {
        "id": "36.72",
        "name": "Lebak",
        "province": "Banten"
    },
    {
        "id": "36.02",
        "name": "Pandeglang",
        "province": "Banten"
    },
    {
        "id": "36.01",
        "name": "Serang",
        "province": "Banten"
    },
    {
        "id": "36.73",
        "name": "Serang",
        "province": "Banten"
    },
    {
        "id": "36.04",
        "name": "Tangerang",
        "province": "Banten"
    },
    {
        "id": "36.71",
        "name": "Tangerang",
        "province": "Banten"
    },
    {
        "id": "36.03",
        "name": "Tangerang Selatan",
        "province": "Banten"
    }
]